LICENSE
MANIFEST.in
README.md
requirements.txt
setup.py
vectortile/Bbox.py
vectortile/Tile.py
vectortile/TileBounds.py
vectortile/TypedMatrix.py
vectortile/__init__.py
vectortile/version.py
vectortile.egg-info/PKG-INFO
vectortile.egg-info/SOURCES.txt
vectortile.egg-info/dependency_links.txt
vectortile.egg-info/requires.txt
vectortile.egg-info/top_level.txt
vectortile/tests/__init__.py
vectortile/tests/test_Bbox.py
vectortile/tests/test_Tile.py
vectortile/tests/test_TileBounds.py
vectortile/tests/test_TypedMatrix.py