Metadata-Version: 2.1
Name: vectortile
Version: 1.4.1
Summary: A set of classes for managing tiles of geospatial vector data
Home-page: https://github.com/emerald-geomodelling/vectortile
Author: Paul Woods, Egil Moeller
Author-email: paul@skytruth.org, em@emrld.no
License: The MIT License (MIT)
License-File: LICENSE
